{"stat.crouchOneCm":3425,"stat.useItem.minecraft.minecart":1,"achievement.openInventory":13,"stat.damageDealt":1480,"stat.mineBlock.minecraft.log":25,"achievement.exploreAllBiomes":{"value":0,"progress":["Plains"]},"stat.mineBlock.minecraft.glass":1,"stat.climbOneCm":816,"stat.useItem.minecraft.stone_pickaxe":1,"stat.fallOneCm":3134,"stat.flyOneCm":9399,"achievement.buildWorkBench":2,"stat.damageTaken":1565,"stat.timeSinceDeath":25408,"stat.leaveGame":2,"stat.diveOneCm":1405,"stat.mineBlock.minecraft.planks":6,"achievement.mineWood":30,"stat.playOneMinute":56032,"stat.useItem.minecraft.stone_shovel":3,"stat.deaths":4,"stat.useItem.minecraft.written_book":1,"stat.useItem.minecraft.stone_axe":55,"stat.swimOneCm":3986,"stat.craftItem.minecraft.crafting_table":1,"stat.furnaceInteraction":2,"stat.playerKills":5,"stat.walkOneCm":164435,"stat.craftItem.minecraft.planks":4,"stat.chestOpened":2,"stat.minecartOneCm":11326,"stat.jump":179,"stat.sprintOneCm":43853}