{"stat.crouchOneCm":1718,"stat.craftingTableInteraction":1,"achievement.openInventory":2,"stat.useItem.minecraft.minecart":1,"stat.damageDealt":1600,"stat.mineBlock.minecraft.log":19,"achievement.exploreAllBiomes":{"value":0,"progress":["Plains"]},"stat.killEntity.Cow":1,"stat.mineBlock.minecraft.glass":6,"stat.useItem.minecraft.stone_pickaxe":18,"stat.fallOneCm":584,"stat.mineBlock.minecraft.iron_ore":5,"stat.flyOneCm":2226,"stat.drop":1,"stat.timeSinceDeath":6342,"stat.leaveGame":1,"stat.playOneMinute":6342,"stat.mineBlock.minecraft.planks":2,"achievement.mineWood":19,"stat.killEntity.Pig":13,"stat.jump":19,"stat.swimOneCm":79,"stat.useItem.minecraft.stone_axe":51,"stat.mobKills":14,"stat.mineBlock.minecraft.stone":6,"stat.walkOneCm":29882,"stat.minecartOneCm":16354,"stat.mineBlock.minecraft.coal_ore":1,"stat.sprintOneCm":5651}