{"stat.crouchOneCm":97710,"stat.mineBlock.minecraft.furnace":12,"stat.craftItem.minecraft.iron_helmet":1,"stat.craftItem.minecraft.wooden_pickaxe":3,"stat.enderchestOpened":29,"stat.killEntity.Sheep":1,"stat.mineBlock.minecraft.sand":2,"stat.mineBlock.minecraft.stained_glass":12,"stat.useItem.minecraft.cobblestone":16,"achievement.exploreAllBiomes":{"value":0,"progress":["Plains"]},"stat.craftItem.minecraft.iron_sword":5,"stat.craftItem.minecraft.iron_pickaxe":14,"stat.craftItem.minecraft.iron_chestplate":1,"stat.mineBlock.minecraft.glass":120,"stat.craftItem.minecraft.wooden_hoe":1,"achievement.acquireIron":53,"stat.craftingTableInteraction":43,"achievement.openInventory":249,"stat.craftItem.minecraft.furnace":6,"stat.damageDealt":8430,"stat.craftItem.minecraft.torch":4,"stat.mineBlock.minecraft.log":96,"stat.killEntity.Cow":10,"stat.fallOneCm":12230,"stat.mineBlock.minecraft.diamond_ore":21,"stat.flyOneCm":506074,"achievement.buildPickaxe":40,"stat.craftItem.minecraft.cooked_beef":15,"stat.mineBlock.minecraft.iron_ore":613,"achievement.buildFurnace":8,"stat.damageTaken":1317004,"stat.useItem.minecraft.torch":4,"stat.craftItem.minecraft.coal":9,"stat.useItem.minecraft.stone_pickaxe":283,"stat.useItem.minecraft.diamond_sword":4,"stat.killEntity.Chicken":12,"stat.craftItem.minecraft.stone_pickaxe":4,"stat.mineBlock.minecraft.cobblestone":13,"stat.mineBlock.minecraft.gold_ore":259,"achievement.buildWorkBench":8,"stat.mineBlock.minecraft.lapis_block":144,"stat.useItem.minecraft.furnace":13,"stat.breakItem.minecraft.stone_pickaxe":1,"stat.craftItem.minecraft.iron_leggings":1,"achievement.killCow":8,"stat.useItem.minecraft.stone_sword":85,"stat.climbOneCm":25532,"stat.drop":25,"achievement.buildHoe":2,"achievement.mineWood":93,"stat.useItem.minecraft.cooked_beef":8,"stat.mineBlock.minecraft.crafting_table":17,"achievement.killEnemy":2,"stat.useItem.minecraft.iron_axe":81,"stat.craftItem.minecraft.dye":837,"achievement.diamonds":20,"stat.useItem.minecraft.cooked_porkchop":7,"stat.killEntity.Creeper":1,"stat.mineBlock.minecraft.planks":22,"stat.useItem.minecraft.crafting_table":20,"stat.playOneMinute":268990,"stat.killEntity.Rabbit":5,"stat.killEntity.Pig":24,"stat.useItem.minecraft.iron_ore":7,"stat.leaveGame":8,"stat.diveOneCm":2674,"stat.craftItem.minecraft.iron_ingot":82,"achievement.buildBetterPickaxe":34,"stat.craftItem.minecraft.leather":1,"stat.timeSinceDeath":40446,"stat.craftItem.minecraft.cooked_porkchop":11,"stat.craftItem.minecraft.stick":68,"achievement.buildSword":10,"stat.swimOneCm":13420,"stat.furnaceInteraction":106,"stat.walkOneCm":1110439,"stat.playerKills":4,"stat.mineBlock.minecraft.coal_ore":266,"stat.jump":1986,"stat.useItem.minecraft.porkchop":2,"stat.mineBlock.minecraft.hay_block":7,"stat.useItem.minecraft.beef":9,"stat.craftItem.minecraft.stone_sword":1,"stat.breakItem.minecraft.iron_pickaxe":9,"stat.useItem.minecraft.iron_sword":28,"stat.deaths":30,"stat.useItem.minecraft.stone_axe":5,"stat.mineBlock.minecraft.gravel":2,"stat.craftItem.minecraft.crafting_table":5,"stat.mobKills":54,"stat.mineBlock.minecraft.stone":1891,"stat.craftItem.minecraft.planks":100,"stat.killEntity.Zombie":1,"stat.chestOpened":58,"stat.useItem.minecraft.wooden_pickaxe":18,"stat.brewingstandInteraction":1,"stat.useItem.minecraft.pumpkin_pie":2,"stat.useItem.minecraft.iron_pickaxe":3072,"stat.craftItem.minecraft.iron_boots":1,"stat.sprintOneCm":380045}