{"stat.crouchOneCm":539,"stat.craftingTableInteraction":3,"achievement.openInventory":20,"stat.damageDealt":2790,"stat.mineBlock.minecraft.log":89,"achievement.exploreAllBiomes":{"value":0,"progress":["Plains"]},"stat.mineBlock.minecraft.glass":13,"stat.killEntity.Cow":1,"stat.useItem.minecraft.stone_pickaxe":278,"stat.fallOneCm":3228,"stat.flyOneCm":57504,"achievement.buildWorkBench":2,"achievement.buildPickaxe":6,"stat.climbOneCm":231,"stat.breakItem.minecraft.stone_pickaxe":2,"stat.mineBlock.minecraft.iron_ore":58,"stat.killEntity.Chicken":2,"stat.damageTaken":130,"stat.mineBlock.minecraft.cobblestone":2,"stat.craftItem.minecraft.stone_pickaxe":3,"stat.leaveGame":2,"stat.diveOneCm":539,"achievement.mineWood":79,"achievement.buildBetterPickaxe":6,"stat.killEntity.Spider":1,"stat.killEntity.Slime":23,"stat.timeSinceDeath":37333,"stat.mineBlock.minecraft.planks":14,"stat.useItem.minecraft.crafting_table":1,"stat.craftItem.minecraft.stick":8,"stat.playOneMinute":37333,"stat.killEntity.Rabbit":1,"stat.killEntity.Pig":7,"stat.jump":324,"stat.useItem.minecraft.porkchop":9,"stat.swimOneCm":499,"stat.useItem.minecraft.stone_axe":152,"stat.craftItem.minecraft.crafting_table":1,"stat.mobKills":35,"stat.mineBlock.minecraft.stone":149,"stat.walkOneCm":174736,"stat.playerKills":1,"stat.breakItem.minecraft.stone_axe":2,"stat.mineBlock.minecraft.coal_ore":50,"stat.sprintOneCm":58280}