{"stat.useItem.minecraft.chest":1,"stat.mineBlock.minecraft.furnace":23,"stat.craftItem.minecraft.coal_block":52,"stat.craftItem.minecraft.wooden_pickaxe":1,"stat.enderchestOpened":363,"stat.craftItem.minecraft.glass_bottle":12,"stat.killEntity.Sheep":2,"stat.mineBlock.minecraft.sand":4,"stat.cakeSlicesEaten":12,"stat.useItem.minecraft.cobblestone":84,"stat.craftItem.minecraft.iron_sword":6,"stat.mineBlock.minecraft.glass":128,"stat.craftItem.minecraft.chest":1,"achievement.acquireIron":110,"stat.useItem.minecraft.minecart":1,"stat.craftingTableInteraction":75,"achievement.openInventory":669,"stat.damageDealt":16640,"stat.useItem.minecraft.experience_bottle":32,"stat.killEntity.Cow":33,"stat.crouchOneCm":159176,"stat.useItem.minecraft.diamond_pickaxe":3335,"stat.mineBlock.minecraft.stained_glass":58,"achievement.exploreAllBiomes":{"value":0,"progress":["Forest","Desert","Ocean","Plains","Jungle"]},"stat.useItem.minecraft.log":29,"stat.craftItem.minecraft.iron_pickaxe":14,"stat.craftItem.minecraft.iron_chestplate":2,"stat.craftItem.minecraft.diamond_chestplate":1,"stat.craftItem.minecraft.furnace":11,"stat.craftItem.minecraft.torch":16,"stat.mineBlock.minecraft.log":51,"achievement.diamondsToYou":3,"stat.fallOneCm":245632,"stat.mineBlock.minecraft.diamond_ore":87,"stat.flyOneCm":1886069,"achievement.buildPickaxe":37,"stat.craftItem.minecraft.cooked_beef":55,"stat.mineBlock.minecraft.iron_ore":1842,"achievement.buildFurnace":16,"stat.damageTaken":30681,"stat.useItem.minecraft.torch":8,"stat.craftItem.minecraft.coal":198,"stat.craftItem.minecraft.bread":138,"stat.useItem.minecraft.stone_pickaxe":249,"stat.mineBlock.minecraft.diamond_block":1,"stat.useItem.minecraft.diamond_sword":7,"stat.mineBlock.minecraft.clay":1,"stat.useItem.minecraft.cake":2,"stat.killEntity.Chicken":3,"stat.craftItem.minecraft.stone_pickaxe":2,"stat.mineBlock.minecraft.cobblestone":113,"stat.mineBlock.minecraft.gold_ore":1035,"achievement.buildWorkBench":28,"stat.useItem.minecraft.stone":2,"stat.mineBlock.minecraft.lapis_block":57,"stat.useItem.minecraft.furnace":27,"stat.craftItem.minecraft.diamond_sword":2,"stat.craftItem.minecraft.gold_block":10,"achievement.killCow":24,"stat.climbOneCm":350489,"stat.useItem.minecraft.potion":12,"stat.drop":212,"stat.craftItem.minecraft.golden_apple":1,"achievement.mineWood":85,"stat.useItem.minecraft.cooked_beef":26,"stat.breakItem.minecraft.diamond_pickaxe":1,"achievement.overpowered":2,"stat.mineBlock.minecraft.crafting_table":15,"stat.useItem.minecraft.iron_axe":11,"stat.useItem.minecraft.glass_bottle":6,"stat.craftItem.minecraft.dye":234,"achievement.diamonds":88,"stat.useItem.minecraft.cooked_porkchop":5,"stat.useItem.minecraft.egg":2,"stat.craftItem.minecraft.diamond_pickaxe":2,"stat.mineBlock.minecraft.planks":6,"stat.useItem.minecraft.lapis_block":12,"stat.useItem.minecraft.crafting_table":22,"stat.playOneMinute":1008322,"stat.craftItem.minecraft.gold_ingot":83,"stat.killEntity.Pig":2,"stat.useItem.minecraft.stone_shovel":16,"stat.useItem.minecraft.chicken":1,"stat.useItem.minecraft.iron_ore":2,"stat.leaveGame":64,"stat.diveOneCm":19664,"stat.craftItem.minecraft.iron_ingot":166,"achievement.buildBetterPickaxe":35,"stat.craftItem.minecraft.bow":2,"stat.timeSinceDeath":196742,"stat.craftItem.minecraft.glass":12,"stat.craftItem.minecraft.cooked_porkchop":14,"stat.craftItem.minecraft.stick":76,"stat.craftItem.minecraft.wheat":450,"achievement.buildSword":16,"stat.craftItem.minecraft.wooden_axe":1,"stat.swimOneCm":41060,"stat.furnaceInteraction":207,"stat.useItem.minecraft.diamond_axe":22,"stat.walkOneCm":4914737,"stat.playerKills":22,"stat.mineBlock.minecraft.coal_ore":325,"stat.useItem.minecraft.bread":38,"stat.jump":10846,"stat.useItem.minecraft.porkchop":6,"stat.mineBlock.minecraft.hay_block":42,"stat.useItem.minecraft.beef":18,"stat.breakItem.minecraft.iron_pickaxe":13,"stat.craftItem.minecraft.lapis_block":3,"stat.useItem.minecraft.iron_sword":92,"stat.useItem.minecraft.written_book":2,"stat.deaths":111,"stat.useItem.minecraft.stone_axe":63,"stat.mineBlock.minecraft.gravel":2,"stat.craftItem.minecraft.crafting_table":15,"stat.mobKills":41,"stat.mineBlock.minecraft.stone":3971,"stat.craftItem.minecraft.planks":156,"stat.chestOpened":127,"stat.minecartOneCm":5042,"stat.useItem.minecraft.wooden_axe":14,"stat.itemEnchanted":8,"stat.useItem.minecraft.wooden_pickaxe":38,"stat.brewingstandInteraction":2,"stat.useItem.minecraft.pumpkin_pie":15,"stat.useItem.minecraft.mutton":4,"stat.useItem.minecraft.iron_pickaxe":4089,"stat.craftItem.minecraft.iron_boots":1,"stat.sprintOneCm":2167431}